odoo/addons/budget_control_purchase_request/README.rst
odoo/addons/budget_control_purchase_request/__init__.py
odoo/addons/budget_control_purchase_request/__manifest__.py
odoo/addons/budget_control_purchase_request/models/__init__.py
odoo/addons/budget_control_purchase_request/models/budget_commit_forward.py
odoo/addons/budget_control_purchase_request/models/budget_control.py
odoo/addons/budget_control_purchase_request/models/budget_period.py
odoo/addons/budget_control_purchase_request/models/purchase.py
odoo/addons/budget_control_purchase_request/models/purchase_budget_move.py
odoo/addons/budget_control_purchase_request/models/purchase_request.py
odoo/addons/budget_control_purchase_request/models/purchase_request_budget_move.py
odoo/addons/budget_control_purchase_request/readme/CONTRIBUTORS.md
odoo/addons/budget_control_purchase_request/readme/DESCRIPTION.md
odoo/addons/budget_control_purchase_request/report/__init__.py
odoo/addons/budget_control_purchase_request/report/budget_common_monitoring.py
odoo/addons/budget_control_purchase_request/report/budget_monitor_report.py
odoo/addons/budget_control_purchase_request/security/ir.model.access.csv
odoo/addons/budget_control_purchase_request/static/description/icon.png
odoo/addons/budget_control_purchase_request/static/description/index.html
odoo/addons/budget_control_purchase_request/tests/__init__.py
odoo/addons/budget_control_purchase_request/tests/test_budget_purchase_request.py
odoo/addons/budget_control_purchase_request/views/budget_commit_forward_view.xml
odoo/addons/budget_control_purchase_request/views/budget_control_view.xml
odoo/addons/budget_control_purchase_request/views/budget_period_view.xml
odoo/addons/budget_control_purchase_request/views/purchase_request_budget_move.xml
odoo/addons/budget_control_purchase_request/views/purchase_request_line_view.xml
odoo/addons/budget_control_purchase_request/views/purchase_request_view.xml
odoo/addons/budget_control_purchase_request/wizards/__init__.py
odoo_addon_budget_control_purchase_request-18.0.1.2.0.dist-info/METADATA
odoo_addon_budget_control_purchase_request-18.0.1.2.0.dist-info/WHEEL
odoo_addon_budget_control_purchase_request-18.0.1.2.0.dist-info/top_level.txt
odoo_addon_budget_control_purchase_request-18.0.1.2.0.dist-info/RECORD
